stix2slider/__init__.py
stix2slider/cli.py
stix2slider/common.py
stix2slider/convert_cyber_observables.py
stix2slider/convert_pattern.py
stix2slider/convert_stix.py
stix2slider/options.py
stix2slider/utils.py
stix2slider/version.py
stix2slider/vocab_mappings.py
stix2_slider-4.0.1.dist-info/LICENSE
stix2_slider-4.0.1.dist-info/METADATA
stix2_slider-4.0.1.dist-info/WHEEL
stix2_slider-4.0.1.dist-info/entry_points.txt
stix2_slider-4.0.1.dist-info/top_level.txt
stix2_slider-4.0.1.dist-info/RECORD
