Metadata-Version: 2.1
Name: stix2-slider
Version: 4.0.1
Summary: Utilities to downgrade STIX 2.1 content to STIX 1.X and CyBOX 2.1
Home-page: https://oasis-open.github.io/cti-documentation/
Author: OASIS Cyber Threat Intelligence Technical Committee
Author-email: cti-users@lists.oasis-open.org
Project-URL: Documentation, https://cti-stix-slider.readthedocs.io/
Project-URL: Source Code, https://github.com/oasis-open/cti-stix-slider/
Project-URL: Bug Tracker, https://github.com/oasis-open/cti-stix-slider/issues/
Keywords: stix stix2 json xml cti cyber threat intelligence
Classifier: Development Status :: 2 - Pre-Alpha
Classifier: Intended Audience :: Developers
Classifier: License :: OSI Approved :: BSD License
Classifier: Operating System :: OS Independent
Classifier: Programming Language :: Python :: 3.8
Classifier: Programming Language :: Python :: 3.9
Classifier: Programming Language :: Python :: 3.10
Classifier: Programming Language :: Python :: 3.11
Classifier: Programming Language :: Python :: 3.12
License-File: LICENSE
Requires-Dist: setuptools
Requires-Dist: stix (<=1.2.1.0,>=1.1.1.9)
Requires-Dist: stix-validator (>=3.0.0)
Requires-Dist: stixmarx (>=1.0.8)
Requires-Dist: stix2 (>=3.0.0)
